flightline/__init__.py
flightline/config_handler.py
flightline/featureclass_handler.py
flightline/flightline_project.py
flightline/folder_handler.py
flightline/width.py
flightline/arctoolbox/Flightline.CopyTracmapDataToGeodatabase.pyt.xml
flightline/arctoolbox/Flightline.CopyTracmapDataToProjectGeodatabase.pyt.xml
flightline/arctoolbox/Flightline.CreateFolderStructure.pyt.xml
flightline/arctoolbox/Flightline.CreateNewFlightDataGdb.pyt.xml
flightline/arctoolbox/Flightline.EnterOrUpdateOperationMetadata.pyt.xml
flightline/arctoolbox/Flightline.ImportTreatmentAreaFeatureclass.pyt.xml
flightline/arctoolbox/Flightline.SummarizeFlightData.pyt.xml
flightline/arctoolbox/Flightline.pyt
flightline/arctoolbox/Flightline.pyt.xml
flightline/data/HelicopterMetadata.json
flightline/data/ProjectSetup.json
flightline/data/flight_path.lyr
flightline/data/flight_path.xml
flightline/data/helicopter_info.xml
flightline/data/operation_start_end_time.xml
flightline/data/sum_totals.xml
flightline/data/total_gdb.xml
flightline/data/total_lines.lyr
flightline/data/total_lines.xml
flightline/data/total_points.lyr
flightline/data/total_points.xml
flightline/data/total_polygons.lyr
flightline/data/total_polygons.xml
flightline-0.81.dist-info/DESCRIPTION.rst
flightline-0.81.dist-info/METADATA
flightline-0.81.dist-info/RECORD
flightline-0.81.dist-info/WHEEL
flightline-0.81.dist-info/metadata.json
flightline-0.81.dist-info/top_level.txt
