Metadata-Version: 2.0
Name: flightline
Version: 0.81
Summary: Python module to manage aerial operations using ESRI ArcMap
Home-page: https://github.com/OSPRI-GIS/flightline
Author: OSPRI
Author-email: gis@ospri.co.nz
License: GNU General Public License v3.0
Keywords: Aerial Tracmap OSPRI
Platform: UNKNOWN
Classifier: Development Status :: 3 - Alpha
Classifier: Operating System :: Microsoft :: Windows
Classifier: Programming Language :: Python
